smokeur/__init__.py
smokeur/cli.py
tests/__init__.py
tests/conftest.py
tests/test_cli.py
smokeur_cli-1.0.0.dist-info/LICENSE
smokeur_cli-1.0.0.dist-info/METADATA
smokeur_cli-1.0.0.dist-info/WHEEL
smokeur_cli-1.0.0.dist-info/entry_points.txt
smokeur_cli-1.0.0.dist-info/top_level.txt
smokeur_cli-1.0.0.dist-info/RECORD
