Metadata-Version: 2.1
Name: smokeur-cli
Version: 1.0.0
Summary: Smokeur client for CLI.
Home-page: https://gitlab.com/c0x6a/smokeur-cli
Author: c0x6a
Author-email: cj@carlosjoel.net
License: BSD
Platform: UNKNOWN
Classifier: Development Status :: 4 - Beta
Classifier: Environment :: Console
Classifier: Intended Audience :: End Users/Desktop
Classifier: License :: OSI Approved :: BSD License
Classifier: Natural Language :: English
Classifier: Operating System :: OS Independent
Classifier: Programming Language :: Python :: 3
Classifier: Topic :: Internet :: WWW/HTTP
Requires-Python: >=3.6
Requires-Dist: requests
Requires-Dist: pyperclip
Requires-Dist: click
Provides-Extra: package
Requires-Dist: bump2version ; extra == 'package'
Requires-Dist: setuptools ; extra == 'package'
Requires-Dist: wheel ; extra == 'package'
Requires-Dist: twine ; extra == 'package'
